MANIFEST.in
requirements.txt
setup.py
sqlsplit/__init__.py
sqlsplit/__main__.py
sqlsplit.egg-info/PKG-INFO
sqlsplit.egg-info/SOURCES.txt
sqlsplit.egg-info/dependency_links.txt
sqlsplit.egg-info/requires.txt
sqlsplit.egg-info/top_level.txt