Metadata-Version: 1.0
Name: sqlsplit
Version: 0.1.0
Summary: A server for splitting sql using sqlformat
Home-page: https://github.com/scopely/sqlsplit
Author: Avram Lyon
Author-email: avram@scopely.com
License: Apache 2.0
Platform: UNKNOWN
